discstore/__init__.py
discstore/adapters/__init__.py
discstore/adapters/inbound/__init__.py
discstore/adapters/inbound/api_controller.py
discstore/adapters/inbound/cli_controller.py
discstore/adapters/inbound/cli_display.py
discstore/adapters/inbound/config.py
discstore/adapters/inbound/interactive_cli_controller.py
discstore/adapters/inbound/ui_controller.py
discstore/adapters/outbound/__init__.py
discstore/adapters/outbound/json_library_adapter.py
discstore/app.py
discstore/di_container.py
discstore/domain/__init__.py
discstore/domain/entities/__init__.py
discstore/domain/repositories/__init__.py
discstore/domain/use_cases/__init__.py
discstore/domain/use_cases/add_disc.py
discstore/domain/use_cases/edit_disc.py
discstore/domain/use_cases/get_disc.py
discstore/domain/use_cases/list_discs.py
discstore/domain/use_cases/remove_disc.py
discstore/domain/use_cases/search_discs.py
jukebox/__init__.py
jukebox/adapters/__init__.py
jukebox/adapters/inbound/__init__.py
jukebox/adapters/inbound/cli_controller.py
jukebox/adapters/inbound/config.py
jukebox/adapters/outbound/__init__.py
jukebox/adapters/outbound/json_library_adapter.py
jukebox/adapters/outbound/players/__init__.py
jukebox/adapters/outbound/players/dryrun_player_adapter.py
jukebox/adapters/outbound/players/sonos_player_adapter.py
jukebox/adapters/outbound/readers/__init__.py
jukebox/adapters/outbound/readers/dryrun_reader_adapter.py
jukebox/adapters/outbound/readers/nfc_reader_adapter.py
jukebox/app.py
jukebox/di_container.py
jukebox/domain/__init__.py
jukebox/domain/entities/__init__.py
jukebox/domain/entities/disc.py
jukebox/domain/entities/library.py
jukebox/domain/entities/playback_action.py
jukebox/domain/entities/playback_session.py
jukebox/domain/entities/tag_event.py
jukebox/domain/ports/__init__.py
jukebox/domain/ports/player_port.py
jukebox/domain/ports/reader_port.py
jukebox/domain/repositories/__init__.py
jukebox/domain/repositories/library_repository.py
jukebox/domain/use_cases/__init__.py
gukebox-0.5.4.dist-info/WHEEL
gukebox-0.5.4.dist-info/entry_points.txt
gukebox-0.5.4.dist-info/METADATA
gukebox-0.5.4.dist-info/RECORD
