Metadata-Version: 2.3
Name: gukebox
Version: 0.5.4
Summary: A Jukebox to play music on speakers using 'CD' with NFC tag
Keywords: jukebox,discstore,music,nfc
Author: Gudsfile
License: MIT License
Classifier: Development Status :: 4 - Beta
Classifier: License :: OSI Approved :: MIT License
Classifier: Operating System :: OS Independent
Classifier: Programming Language :: Python :: 3 :: Only
Classifier: Programming Language :: Python :: 3.8
Classifier: Programming Language :: Python :: 3.9
Classifier: Programming Language :: Python :: 3.10
Classifier: Programming Language :: Python :: 3.11
Classifier: Programming Language :: Python :: 3.12
Classifier: Programming Language :: Python :: 3.13
Requires-Dist: pydantic==2.5.3 ; python_full_version < '3.10'
Requires-Dist: pydantic==2.10.6 ; python_full_version >= '3.10' and python_full_version < '3.13'
Requires-Dist: pydantic==2.12.5 ; python_full_version >= '3.13'
Requires-Dist: soco==0.30.14
Requires-Dist: fastapi==0.124.4 ; extra == 'api'
Requires-Dist: uvicorn==0.33.0 ; python_full_version < '3.9' and extra == 'api'
Requires-Dist: uvicorn==0.38.0 ; python_full_version >= '3.10' and extra == 'api'
Requires-Dist: pyserial==3.5 ; extra == 'nfc'
Requires-Dist: rpi-gpio==0.7.1 ; extra == 'nfc'
Requires-Dist: spidev==3.8 ; extra == 'nfc'
Requires-Dist: gukebox[api] ; extra == 'ui'
Requires-Dist: fastui==0.8.0 ; python_full_version >= '3.10' and extra == 'ui'
Requires-Dist: python-multipart==0.0.20 ; python_full_version >= '3.10' and extra == 'ui'
Requires-Python: >=3.8, <3.14
Project-URL: Repository, https://github.com/Gudsfile/jukebox
Provides-Extra: api
Provides-Extra: nfc
Provides-Extra: ui
